LICENSE
MANIFEST.in
README.rst
setup.py
django_phonotactics.egg-info/PKG-INFO
django_phonotactics.egg-info/SOURCES.txt
django_phonotactics.egg-info/dependency_links.txt
django_phonotactics.egg-info/top_level.txt
phonotactics/__init__.py
phonotactics/admin.py
phonotactics/apps.py
phonotactics/calculator.py
phonotactics/forms.py
phonotactics/mappings.py
phonotactics/middleware.py
phonotactics/models.py
phonotactics/tests.py
phonotactics/urls.py
phonotactics/utils.py
phonotactics/views.py
phonotactics/widgets.py
phonotactics/migrations/0001_initial.py
phonotactics/migrations/__init__.py
phonotactics/static/css/bundle.css
phonotactics/static/css/jquery-ui.min.css
phonotactics/static/css/main.css
phonotactics/static/css/style.css
phonotactics/static/img/background.jpg
phonotactics/static/js/bundle.js
phonotactics/static/js/jquery-1.10.2.min.js
phonotactics/static/js/jquery-ui.min.js
phonotactics/templates/base.html
phonotactics/templates/done.html
phonotactics/templates/integer-range-field.html
phonotactics/templates/wizard_form.html