Metadata-Version: 1.1
Name: django-phonotactics
Version: 0.1.1
Summary: A Django app for calculating phonotactic probabilities in Serbian language.
Home-page: https://www.phonotactics.ml/
Author: Nikola Paunović
Author-email: ludi.macow@gmail.com
License: MIT License
Platform: UNKNOWN
Classifier: Environment :: Web Environment
Classifier: Framework :: Django
Classifier: Framework :: Django :: 1.10
Classifier: Intended Audience :: Developers
Classifier: License :: OSI Approved :: MIT License
Classifier: Operating System :: OS Independent
Classifier: Programming Language :: Python
Classifier: Programming Language :: Python :: 2.7
Classifier: Topic :: Internet :: WWW/HTTP
Classifier: Topic :: Internet :: WWW/HTTP :: Dynamic Content
